dnif/__init__.py
dnif/consumer.py
dnif/exception.py
dnif/logger.py
dnif_logger-1.0.1.dist-info/DESCRIPTION.rst
dnif_logger-1.0.1.dist-info/METADATA
dnif_logger-1.0.1.dist-info/RECORD
dnif_logger-1.0.1.dist-info/WHEEL
dnif_logger-1.0.1.dist-info/metadata.json
dnif_logger-1.0.1.dist-info/top_level.txt
