Metadata-Version: 2.0
Name: dnif-logger
Version: 1.0.1
Summary: DNIF Logging Client Library
Home-page: https://github.com/dnif/dnif-logger
Author: Bhumil Haria
Author-email: bhumilharia@gmail.com
License: Apache
Keywords: dnif logging analytics
Platform: UNKNOWN
Classifier: Development Status :: 4 - Beta
Classifier: Intended Audience :: Developers
Classifier: Topic :: Software Development :: Libraries :: Python Modules
Classifier: License :: OSI Approved :: Apache Software License
Classifier: Programming Language :: Python :: 2
Classifier: Programming Language :: Python :: 2.7
Classifier: Programming Language :: Python :: 3
Classifier: Programming Language :: Python :: 3.3
Classifier: Programming Language :: Python :: 3.4
Classifier: Programming Language :: Python :: 3.5
Requires-Dist: requests
